aalto_asr_preprocessor/__init__.py
aalto_asr_preprocessor/__main__.py
aalto_asr_preprocessor/fi/__init__.py
aalto_asr_preprocessor/fi/numbers/__init__.py
aalto_asr_preprocessor/fi/numbers/expansion.py
aalto_asr_preprocessor/fi/parl_to_kaldi_text.py
aalto_asr_preprocessor/fi/words_elative.txt
aalto_asr_preprocessor/preprocessor.py
aalto_asr_preprocessor/py.typed
aalto_asr_preprocessor-2022.4.27.dist-info/entry_points.txt
aalto_asr_preprocessor-2022.4.27.dist-info/LICENSE.rst
aalto_asr_preprocessor-2022.4.27.dist-info/WHEEL
aalto_asr_preprocessor-2022.4.27.dist-info/METADATA
aalto_asr_preprocessor-2022.4.27.dist-info/RECORD
