Metadata-Version: 2.1
Name: aalto-asr-preprocessor
Version: 2022.4.27
Summary: Aalto ASR preprocessing tool for preparing texts.
Home-page: https://github.com/aalto-speech/aalto-asr-preprocessor
License: MIT
Keywords: aalto,ASR,preprocessor
Author: Anja Virkkunen
Author-email: anja.virkkunen@aalto.fi
Requires-Python: >=3.8,<4.0
Classifier: License :: OSI Approved :: MIT License
Classifier: Programming Language :: Python :: 3
Classifier: Programming Language :: Python :: 3.10
Classifier: Programming Language :: Python :: 3.8
Classifier: Programming Language :: Python :: 3.9
Requires-Dist: click (>=8.0.1,<9.0.0)
Project-URL: Repository, https://github.com/aalto-speech/aalto-asr-preprocessor
